[
  {
    "german": "01 eins",
    "english": "one",
    "gender": "",
    "class": "num",
    "topic": "num"
  },
  {
    "german": "02 zwei",
    "english": "two",
    "gender": "",
    "class": "num",
    "topic": "num"
  },
  {
    "german": "03 drei",
    "english": "three",
    "gender": "",
    "class": "num",
    "topic": "num"
  },
  {
    "german": "04 vier",
    "english": "four",
    "gender": "",
    "class": "num",
    "topic": "num"
  },
  {
    "german": "05 fünf",
    "english": "five",
    "gender": "",
    "class": "num",
    "topic": "num"
  },
  {
    "german": "06 sechs",
    "english": "six",
    "gender": "",
    "class": "num",
    "topic": "num"
  },
  {
    "german": "07 sieben",
    "english": "seven",
    "gender": "",
    "class": "num",
    "topic": "num"
  },
  {
    "german": "08 acht",
    "english": "eight",
    "gender": "",
    "class": "num",
    "topic": "num"
  },
  {
    "german": "09 neun",
    "english": "nine",
    "gender": "",
    "class": "num",
    "topic": "num"
  },
  {
    "german": "1.000 tausend",
    "english": "thausand",
    "gender": "",
    "class": "num",
    "topic": "num"
  },
  {
    "german": "1.000.000 eine million",
    "english": "one million",
    "gender": "",
    "class": "num",
    "topic": "num"
  },
  {
    "german": "10 zehn",
    "english": "ten",
    "gender": "",
    "class": "num",
    "topic": "num"
  },
  {
    "german": "10.000 zehntausend",
    "english": "ten thausand",
    "gender": "",
    "class": "num",
    "topic": "num"
  },
  {
    "german": "100 einhundert",
    "english": "one hundred",
    "gender": "",
    "class": "num",
    "topic": "num"
  },
  {
    "german": "100.000 hunderttausend",
    "english": "hundred thausand",
    "gender": "",
    "class": "num",
    "topic": "num"
  },
  {
    "german": "101 einhundertundeins",
    "english": "one hundred and one",
    "gender": "",
    "class": "num",
    "topic": "num"
  },
  {
    "german": "11 elf",
    "english": "eleven",
    "gender": "",
    "class": "num",
    "topic": "num"
  },
  {
    "german": "110 einhundertzehn",
    "english": "one hundred ten",
    "gender": "",
    "class": "num",
    "topic": "num"
  },
  {
    "german": "111 einhundertelf",
    "english": "one hundred eleven",
    "gender": "",
    "class": "num",
    "topic": "num"
  },
  {
    "german": "12 zwölf",
    "english": "twelve",
    "gender": "",
    "class": "num",
    "topic": "num"
  },
  {
    "german": "120 einhundertzwanzig",
    "english": "one hundred twenty",
    "gender": "",
    "class": "num",
    "topic": "num"
  },
  {
    "german": "13 dreizehn",
    "english": "thirteen",
    "gender": "",
    "class": "num",
    "topic": "num"
  },
  {
    "german": "14 vierzehn",
    "english": "fourteen",
    "gender": "",
    "class": "num",
    "topic": "num"
  },
  {
    "german": "15 fünfzehn",
    "english": "fifteen",
    "gender": "",
    "class": "num",
    "topic": "num"
  },
  {
    "german": "16 sechzehn",
    "english": "sixteen",
    "gender": "",
    "class": "num",
    "topic": "num"
  },
  {
    "german": "17 siebzehn",
    "english": "seventeen",
    "gender": "",
    "class": "num",
    "topic": "num"
  },
  {
    "german": "18 achtzehn",
    "english": "eighteen",
    "gender": "",
    "class": "num",
    "topic": "num"
  },
  {
    "german": "19 neunzehn",
    "english": "nineteen",
    "gender": "",
    "class": "num",
    "topic": "num"
  },
  {
    "german": "20 zwanzig",
    "english": "twenty",
    "gender": "",
    "class": "num",
    "topic": "num"
  },
  {
    "german": "200 zweihundert",
    "english": "two hundred",
    "gender": "",
    "class": "num",
    "topic": "num"
  },
  {
    "german": "21 einundzwanzig",
    "english": "twenty-one",
    "gender": "",
    "class": "num",
    "topic": "num"
  },
  {
    "german": "22 zweiundzwanzig",
    "english": "twenty-two",
    "gender": "",
    "class": "num",
    "topic": "num"
  },
  {
    "german": "23 dreiundzwanzig",
    "english": "twenty-three",
    "gender": "",
    "class": "num",
    "topic": "num"
  },
  {
    "german": "24 vierundzwanzig",
    "english": "twenty-four",
    "gender": "",
    "class": "num",
    "topic": "num"
  },
  {
    "german": "25 fünfundzwanzig",
    "english": "twenty-five",
    "gender": "",
    "class": "num",
    "topic": "num"
  },
  {
    "german": "26 sechsundzwanzig",
    "english": "twenty-six",
    "gender": "",
    "class": "num",
    "topic": "num"
  },
  {
    "german": "27 siebenundzwanzig",
    "english": "twenty-seven",
    "gender": "",
    "class": "num",
    "topic": "num"
  },
  {
    "german": "28 achtundzwanzig",
    "english": "twenty-eight",
    "gender": "",
    "class": "num",
    "topic": "num"
  },
  {
    "german": "29 neunundzwanzig",
    "english": "twenty-nine",
    "gender": "",
    "class": "num",
    "topic": "num"
  },
  {
    "german": "30 dreißig",
    "english": "thirty",
    "gender": "",
    "class": "num",
    "topic": "num"
  },
  {
    "german": "300 dreihundert",
    "english": "three hundred",
    "gender": "",
    "class": "num",
    "topic": "num"
  },
  {
    "german": "31 einunddreißig",
    "english": "thirty-one",
    "gender": "",
    "class": "num",
    "topic": "num"
  },
  {
    "german": "40 vierzig",
    "english": "fourty",
    "gender": "",
    "class": "num",
    "topic": "num"
  },
  {
    "german": "400 vierhundert",
    "english": "four hundred",
    "gender": "",
    "class": "num",
    "topic": "num"
  },
  {
    "german": "50 fünfzig",
    "english": "fifty",
    "gender": "",
    "class": "num",
    "topic": "num"
  },
  {
    "german": "500 fünfhundert",
    "english": "five hundred",
    "gender": "",
    "class": "num",
    "topic": "num"
  },
  {
    "german": "60 sechzig",
    "english": "sixty",
    "gender": "",
    "class": "num",
    "topic": "num"
  },
  {
    "german": "600 sechshundert",
    "english": "six hundred",
    "gender": "",
    "class": "num",
    "topic": "num"
  },
  {
    "german": "70 siebzig",
    "english": "seventy",
    "gender": "",
    "class": "num",
    "topic": "num"
  },
  {
    "german": "700 siebenhundert",
    "english": "seven hundred",
    "gender": "",
    "class": "num",
    "topic": "num"
  },
  {
    "german": "80 achtzig",
    "english": "eighty",
    "gender": "",
    "class": "num",
    "topic": "num"
  },
  {
    "german": "800 achhundert",
    "english": "eight hundred",
    "gender": "",
    "class": "num",
    "topic": "num"
  },
  {
    "german": "90 neunzig",
    "english": "ninety",
    "gender": "",
    "class": "num",
    "topic": "num"
  },
  {
    "german": "900 neunhundert",
    "english": "nine hundred",
    "gender": "",
    "class": "num",
    "topic": "num"
  },
  {
    "german": "abend",
    "english": "evening",
    "gender": "m",
    "class": "noun",
    "topic": "time"
  },
  {
    "german": "abhängen",
    "english": "to depend",
    "gender": "",
    "class": "verb",
    "topic": ""
  },
  {
    "german": "abholen",
    "english": "to fetch",
    "gender": "",
    "class": "verb",
    "topic": ""
  },
  {
    "german": "abschied",
    "english": "farewell",
    "gender": "m",
    "class": "noun",
    "topic": ""
  },
  {
    "german": "adresse",
    "english": "address",
    "gender": "f",
    "class": "noun",
    "topic": "house"
  },
  {
    "german": "affe",
    "english": "monkey",
    "gender": "m",
    "class": "noun",
    "topic": "animal"
  },
  {
    "german": "alkohol",
    "english": "alcohol",
    "gender": "m",
    "class": "noun",
    "topic": "food"
  },
  {
    "german": "alt",
    "english": "old",
    "gender": "",
    "class": "adj",
    "topic": ""
  },
  {
    "german": "alter",
    "english": "age",
    "gender": "n",
    "class": "noun",
    "topic": ""
  },
  {
    "german": "analysieren",
    "english": "to analyze",
    "gender": "",
    "class": "verb",
    "topic": ""
  },
  {
    "german": "angebot",
    "english": "offer",
    "gender": "n",
    "class": "noun",
    "topic": "monetary"
  },
  {
    "german": "ankommen",
    "english": "to arrive",
    "gender": "",
    "class": "verb",
    "topic": ""
  },
  {
    "german": "apfel",
    "english": "apple",
    "gender": "m",
    "class": "noun",
    "topic": "fruit"
  },
  {
    "german": "äpfel",
    "english": "apples",
    "gender": "p",
    "class": "noun",
    "topic": "fruit"
  },
  {
    "german": "arbeiten",
    "english": "to work",
    "gender": "",
    "class": "verb",
    "topic": "profession"
  },
  {
    "german": "arbeitszimmer",
    "english": "study (room)",
    "gender": "n",
    "class": "noun",
    "topic": "house"
  },
  {
    "german": "archiv",
    "english": "archives",
    "gender": "n",
    "class": "noun",
    "topic": "office"
  },
  {
    "german": "arm",
    "english": "poor",
    "gender": "",
    "class": "adj",
    "topic": ""
  },
  {
    "german": "arzt",
    "english": "doctor",
    "gender": "m",
    "class": "noun",
    "topic": "profession"
  },
  {
    "german": "ärztin",
    "english": "doctor",
    "gender": "f",
    "class": "noun",
    "topic": "profession"
  },
  {
    "german": "aufgeben",
    "english": "to give up",
    "gender": "",
    "class": "verb",
    "topic": ""
  },
  {
    "german": "aufwachen",
    "english": "to wake up",
    "gender": "",
    "class": "verb",
    "topic": ""
  },
  {
    "german": "auge",
    "english": "eye",
    "gender": "n",
    "class": "verb",
    "topic": "anatomy"
  },
  {
    "german": "augenbraue",
    "english": "eyebrow",
    "gender": "f",
    "class": "verb",
    "topic": "anatomy"
  },
  {
    "german": "ausbildung",
    "english": "education",
    "gender": "f",
    "class": "noun",
    "topic": ""
  },
  {
    "german": "ausnutzen",
    "english": "to exploit",
    "gender": "",
    "class": "verb",
    "topic": "profession"
  },
  {
    "german": "ausradieren",
    "english": "to erase",
    "gender": "",
    "class": "verb",
    "topic": ""
  },
  {
    "german": "aussprechen",
    "english": "to pronounce",
    "gender": "",
    "class": "verb",
    "topic": ""
  },
  {
    "german": "auto",
    "english": "car",
    "gender": "n",
    "class": "noun",
    "topic": "transportation"
  },
  {
    "german": "autos",
    "english": "cars",
    "gender": "p",
    "class": "noun",
    "topic": "transportation"
  },
  {
    "german": "baby",
    "english": "baby",
    "gender": "n",
    "class": "noun",
    "topic": "family"
  },
  {
    "german": "bäckerei",
    "english": "bakery",
    "gender": "f",
    "class": "noun",
    "topic": ""
  },
  {
    "german": "bad",
    "english": "bath",
    "gender": "n",
    "class": "noun",
    "topic": "house"
  },
  {
    "german": "badewanne",
    "english": "bath(tub)",
    "gender": "f",
    "class": "noun",
    "topic": "house"
  },
  {
    "german": "badzimmer",
    "english": "bathroom",
    "gender": "n",
    "class": "noun",
    "topic": "house"
  },
  {
    "german": "balkon",
    "english": "balcony",
    "gender": "m",
    "class": "noun",
    "topic": "house"
  },
  {
    "german": "ball",
    "english": "ball",
    "gender": "m",
    "class": "noun",
    "topic": "sport"
  },
  {
    "german": "banane",
    "english": "banana",
    "gender": "f",
    "class": "noun",
    "topic": "food"
  },
  {
    "german": "bauch",
    "english": "belly",
    "gender": "m",
    "class": "verb",
    "topic": "anatomy"
  },
  {
    "german": "bauen",
    "english": "to build",
    "gender": "",
    "class": "verb",
    "topic": ""
  },
  {
    "german": "becher",
    "english": "cup",
    "gender": "m",
    "class": "noun",
    "topic": "container"
  },
  {
    "german": "bedeuten",
    "english": "to mean (= signify)",
    "gender": "",
    "class": "verb",
    "topic": ""
  },
  {
    "german": "begraben",
    "english": "to bury",
    "gender": "",
    "class": "verb",
    "topic": ""
  },
  {
    "german": "begrüßung",
    "english": "greeting",
    "gender": "f",
    "class": "noun",
    "topic": ""
  },
  {
    "german": "bein",
    "english": "leg",
    "gender": "n",
    "class": "verb",
    "topic": "anatomy"
  },
  {
    "german": "beispiel",
    "english": "example",
    "gender": "n",
    "class": "noun",
    "topic": ""
  },
  {
    "german": "benutzen",
    "english": "to use",
    "gender": "",
    "class": "verb",
    "topic": ""
  },
  {
    "german": "bereits",
    "english": "already",
    "gender": "",
    "class": "adv",
    "topic": ""
  },
  {
    "german": "beruf",
    "english": "profession",
    "gender": "m",
    "class": "noun",
    "topic": "profession"
  },
  {
    "german": "besuchen",
    "english": "to visit",
    "gender": "",
    "class": "verb",
    "topic": ""
  },
  {
    "german": "beten",
    "english": "to pray",
    "gender": "",
    "class": "verb",
    "topic": ""
  },
  {
    "german": "bett",
    "english": "bed",
    "gender": "n",
    "class": "noun",
    "topic": "furniture"
  },
  {
    "german": "bier",
    "english": "beer",
    "gender": "n",
    "class": "noun",
    "topic": "food"
  },
  {
    "german": "bild",
    "english": "picture",
    "gender": "n",
    "class": "noun",
    "topic": "furniture"
  },
  {
    "german": "billig",
    "english": "cheap",
    "gender": "",
    "class": "adj",
    "topic": "monetary"
  },
  {
    "german": "biologie",
    "english": "biology",
    "gender": "f",
    "class": "noun",
    "topic": "anatomy"
  },
  {
    "german": "birne",
    "english": "pear",
    "gender": "f",
    "class": "noun",
    "topic": "food"
  },
  {
    "german": "bitten",
    "english": "to ask (favor)",
    "gender": "",
    "class": "verb",
    "topic": ""
  },
  {
    "german": "blau",
    "english": "blue",
    "gender": "",
    "class": "adj",
    "topic": "color"
  },
  {
    "german": "bleistift",
    "english": "pencil",
    "gender": "m",
    "class": "noun",
    "topic": "office"
  },
  {
    "german": "blume",
    "english": "flower",
    "gender": "f",
    "class": "noun",
    "topic": "plant"
  },
  {
    "german": "blut",
    "english": "blood",
    "gender": "n",
    "class": "verb",
    "topic": "anatomy"
  },
  {
    "german": "bluten",
    "english": "to bleed",
    "gender": "",
    "class": "verb",
    "topic": "anatomy"
  },
  {
    "german": "boot",
    "english": "boat",
    "gender": "n",
    "class": "noun",
    "topic": "transportation"
  },
  {
    "german": "brauchen",
    "english": "to need",
    "gender": "",
    "class": "verb",
    "topic": ""
  },
  {
    "german": "braun",
    "english": "brown",
    "gender": "",
    "class": "adj",
    "topic": "color"
  },
  {
    "german": "breit",
    "english": "broad",
    "gender": "",
    "class": "adj",
    "topic": ""
  },
  {
    "german": "brief",
    "english": "letter",
    "gender": "m",
    "class": "noun",
    "topic": "office"
  },
  {
    "german": "brille",
    "english": "glasses",
    "gender": "f",
    "class": "noun",
    "topic": "accessories"
  },
  {
    "german": "bringen",
    "english": "to bring",
    "gender": "",
    "class": "verb",
    "topic": ""
  },
  {
    "german": "brot",
    "english": "bread",
    "gender": "n",
    "class": "noun",
    "topic": "food"
  },
  {
    "german": "brötchen",
    "english": "little bread",
    "gender": "n",
    "class": "noun",
    "topic": "food"
  },
  {
    "german": "brote",
    "english": "breads",
    "gender": "p",
    "class": "noun",
    "topic": "food"
  },
  {
    "german": "bruder",
    "english": "brother",
    "gender": "m",
    "class": "noun",
    "topic": "family"
  },
  {
    "german": "brüder",
    "english": "brothers",
    "gender": "p",
    "class": "noun",
    "topic": "family"
  },
  {
    "german": "brust",
    "english": "chest",
    "gender": "f",
    "class": "verb",
    "topic": "anatomy"
  },
  {
    "german": "buch",
    "english": "book",
    "gender": "n",
    "class": "noun",
    "topic": "office"
  },
  {
    "german": "bücher",
    "english": "books",
    "gender": "p",
    "class": "noun",
    "topic": "office"
  },
  {
    "german": "buchstabieren",
    "english": "to spell",
    "gender": "",
    "class": "verb",
    "topic": "office"
  },
  {
    "german": "bus",
    "english": "bus",
    "gender": "m",
    "class": "noun",
    "topic": "transportation"
  },
  {
    "german": "butter",
    "english": "butter",
    "gender": "f",
    "class": "noun",
    "topic": "food"
  },
  {
    "german": "café",
    "english": "café",
    "gender": "n",
    "class": "noun",
    "topic": "food"
  },
  {
    "german": "cent",
    "english": "cent",
    "gender": "m",
    "class": "noun",
    "topic": "monetary"
  },
  {
    "german": "cousin",
    "english": "cousin",
    "gender": "m",
    "class": "noun",
    "topic": "family"
  },
  {
    "german": "cousine",
    "english": "cousin",
    "gender": "f",
    "class": "noun",
    "topic": "family"
  },
  {
    "german": "da",
    "english": "here",
    "gender": "",
    "class": "adv",
    "topic": ""
  },
  {
    "german": "denken",
    "english": "to think",
    "gender": "",
    "class": "verb",
    "topic": ""
  },
  {
    "german": "ding",
    "english": "thing",
    "gender": "n",
    "class": "noun",
    "topic": "container"
  },
  {
    "german": "doktor",
    "english": "doctor",
    "gender": "m",
    "class": "noun",
    "topic": "profession"
  },
  {
    "german": "doktorin",
    "english": "doctor",
    "gender": "f",
    "class": "noun",
    "topic": "profession"
  },
  {
    "german": "dorf",
    "english": "village",
    "gender": "n",
    "class": "noun",
    "topic": ""
  },
  {
    "german": "dort",
    "english": "there",
    "gender": "",
    "class": "adv",
    "topic": ""
  },
  {
    "german": "dose",
    "english": "can",
    "gender": "f",
    "class": "noun",
    "topic": "container"
  },
  {
    "german": "draußen",
    "english": "outside / outdoors",
    "gender": "",
    "class": "adv",
    "topic": ""
  },
  {
    "german": "dunkel",
    "english": "dark",
    "gender": "",
    "class": "adj",
    "topic": "color"
  },
  {
    "german": "dunkelrot",
    "english": "dark red",
    "gender": "",
    "class": "adj",
    "topic": "color"
  },
  {
    "german": "dusche",
    "english": "shower",
    "gender": "f",
    "class": "noun",
    "topic": "house"
  },
  {
    "german": "ehrlich",
    "english": "honest",
    "gender": "",
    "class": "adj",
    "topic": ""
  },
  {
    "german": "ehrlichkeit",
    "english": "honesty",
    "gender": "n",
    "class": "noun",
    "topic": ""
  },
  {
    "german": "ei",
    "english": "egg",
    "gender": "n",
    "class": "noun",
    "topic": "food"
  },
  {
    "german": "eier",
    "english": "eggs",
    "gender": "p",
    "class": "noun",
    "topic": "food"
  },
  {
    "german": "eigentlich",
    "english": "actually",
    "gender": "",
    "class": "adv",
    "topic": ""
  },
  {
    "german": "eine Predigt halten",
    "english": "to preach",
    "gender": "",
    "class": "verb",
    "topic": ""
  },
  {
    "german": "einfach",
    "english": "easy",
    "gender": "",
    "class": "adj",
    "topic": ""
  },
  {
    "german": "einkaufswagen",
    "english": "shopping cart",
    "gender": "m",
    "class": "noun",
    "topic": ""
  },
  {
    "german": "einladen",
    "english": "to invite",
    "gender": "",
    "class": "verb",
    "topic": ""
  },
  {
    "german": "einschlafen",
    "english": "to fall asleep",
    "gender": "",
    "class": "verb",
    "topic": ""
  },
  {
    "german": "eis",
    "english": "ice",
    "gender": "n",
    "class": "noun",
    "topic": "element"
  },
  {
    "german": "ellbogen",
    "english": "elbow",
    "gender": "m",
    "class": "verb",
    "topic": "anatomy"
  },
  {
    "german": "eltern",
    "english": "parents",
    "gender": "p",
    "class": "noun",
    "topic": "family"
  },
  {
    "german": "endung",
    "english": "ending",
    "gender": "f",
    "class": "noun",
    "topic": ""
  },
  {
    "german": "enkel",
    "english": "grandson",
    "gender": "m",
    "class": "noun",
    "topic": "family"
  },
  {
    "german": "enkelin",
    "english": "granddaughter",
    "gender": "f",
    "class": "noun",
    "topic": "family"
  },
  {
    "german": "ente",
    "english": "duck",
    "gender": "f",
    "class": "noun",
    "topic": "animal"
  },
  {
    "german": "erklären",
    "english": "to explain",
    "gender": "",
    "class": "verb",
    "topic": ""
  },
  {
    "german": "ermüden",
    "english": "to get tired",
    "gender": "",
    "class": "verb",
    "topic": ""
  },
  {
    "german": "ertränken",
    "english": "to drown",
    "gender": "",
    "class": "verb",
    "topic": ""
  },
  {
    "german": "erzählen",
    "english": "to tell",
    "gender": "",
    "class": "verb",
    "topic": ""
  },
  {
    "german": "erzieher",
    "english": "teacher",
    "gender": "m",
    "class": "noun",
    "topic": "profession"
  },
  {
    "german": "erzieherin",
    "english": "teacher",
    "gender": "f",
    "class": "noun",
    "topic": "profession"
  },
  {
    "german": "essen",
    "english": "to eat",
    "gender": "",
    "class": "verb",
    "topic": "food"
  },
  {
    "german": "euro",
    "english": "euro",
    "gender": "m",
    "class": "noun",
    "topic": "monetary"
  },
  {
    "german": "fahrkarte",
    "english": "ticket",
    "gender": "f",
    "class": "noun",
    "topic": "transportation"
  },
  {
    "german": "fantastisch",
    "english": "fantastic",
    "gender": "",
    "class": "adj",
    "topic": ""
  },
  {
    "german": "farbe",
    "english": "colour",
    "gender": "f",
    "class": "noun",
    "topic": "color"
  },
  {
    "german": "fast",
    "english": "almost",
    "gender": "",
    "class": "adv",
    "topic": ""
  },
  {
    "german": "fenster",
    "english": "window",
    "gender": "n",
    "class": "noun",
    "topic": "house"
  },
  {
    "german": "fernsehen",
    "english": "television",
    "gender": "m",
    "class": "noun",
    "topic": "furniture"
  },
  {
    "german": "ferse",
    "english": "heel",
    "gender": "f",
    "class": "verb",
    "topic": "anatomy"
  },
  {
    "german": "feuer",
    "english": "fire",
    "gender": "n",
    "class": "noun",
    "topic": "food"
  },
  {
    "german": "film",
    "english": "movie / film",
    "gender": "m",
    "class": "noun",
    "topic": "entertainment"
  },
  {
    "german": "finden",
    "english": "to find",
    "gender": "",
    "class": "verb",
    "topic": ""
  },
  {
    "german": "finger",
    "english": "finger",
    "gender": "m",
    "class": "verb",
    "topic": "anatomy"
  },
  {
    "german": "fisch",
    "english": "fish",
    "gender": "m",
    "class": "noun",
    "topic": "animal"
  },
  {
    "german": "flasche",
    "english": "bottle",
    "gender": "f",
    "class": "noun",
    "topic": "container"
  },
  {
    "german": "fleisch",
    "english": "meat",
    "gender": "n",
    "class": "noun",
    "topic": "food"
  },
  {
    "german": "fleischtheke",
    "english": "meat counter",
    "gender": "f",
    "class": "noun",
    "topic": ""
  },
  {
    "german": "fleiß",
    "english": "dilligence",
    "gender": "m",
    "class": "noun",
    "topic": ""
  },
  {
    "german": "fleißig",
    "english": "dilligent",
    "gender": "",
    "class": "adj",
    "topic": ""
  },
  {
    "german": "fliege",
    "english": "fly",
    "gender": "f",
    "class": "noun",
    "topic": "animal"
  },
  {
    "german": "fliegen",
    "english": "to fly",
    "gender": "",
    "class": "verb",
    "topic": ""
  },
  {
    "german": "floh",
    "english": "flea",
    "gender": "m",
    "class": "noun",
    "topic": "animal"
  },
  {
    "german": "fluchen",
    "english": "to swear (use bad words)",
    "gender": "",
    "class": "verb",
    "topic": ""
  },
  {
    "german": "flügel",
    "english": "wing",
    "gender": "m",
    "class": "verb",
    "topic": "animal"
  },
  {
    "german": "flugzeug",
    "english": "airplane",
    "gender": "n",
    "class": "noun",
    "topic": "transportation"
  },
  {
    "german": "flur",
    "english": "hall / corridor",
    "gender": "m",
    "class": "noun",
    "topic": "house"
  },
  {
    "german": "forschen",
    "english": "to research",
    "gender": "",
    "class": "verb",
    "topic": ""
  },
  {
    "german": "foto",
    "english": "photo",
    "gender": "n",
    "class": "noun",
    "topic": "furniture"
  },
  {
    "german": "fotografieren",
    "english": "to photograph",
    "gender": "",
    "class": "verb",
    "topic": ""
  },
  {
    "german": "fotolabor",
    "english": "photo lab",
    "gender": "n",
    "class": "noun",
    "topic": ""
  },
  {
    "german": "frage",
    "english": "question",
    "gender": "f",
    "class": "noun",
    "topic": ""
  },
  {
    "german": "fragen",
    "english": "to ask (question)",
    "gender": "",
    "class": "verb",
    "topic": ""
  },
  {
    "german": "frau",
    "english": "woman",
    "gender": "f",
    "class": "noun",
    "topic": "family"
  },
  {
    "german": "freiheit",
    "english": "freedom",
    "gender": "f",
    "class": "noun",
    "topic": ""
  },
  {
    "german": "frisch",
    "english": "fresh",
    "gender": "",
    "class": "adj",
    "topic": ""
  },
  {
    "german": "frühling",
    "english": "spring",
    "gender": "m",
    "class": "noun",
    "topic": "nature"
  },
  {
    "german": "fuß",
    "english": "foot",
    "gender": "m",
    "class": "verb",
    "topic": "anatomy"
  },
  {
    "german": "fußball",
    "english": "football",
    "gender": "m",
    "class": "noun",
    "topic": "sport"
  },
  {
    "german": "geboren",
    "english": "to be born",
    "gender": "",
    "class": "verb",
    "topic": "family"
  },
  {
    "german": "gefallen",
    "english": "to pease s.b.",
    "gender": "",
    "class": "verb",
    "topic": ""
  },
  {
    "german": "gegenteil",
    "english": "opposite",
    "gender": "n",
    "class": "noun",
    "topic": ""
  },
  {
    "german": "gehen",
    "english": "to go",
    "gender": "",
    "class": "verb",
    "topic": ""
  },
  {
    "german": "gelb",
    "english": "yellow",
    "gender": "",
    "class": "adj",
    "topic": "color"
  },
  {
    "german": "geld",
    "english": "money",
    "gender": "n",
    "class": "noun",
    "topic": "monetary"
  },
  {
    "german": "geldautomat",
    "english": "atm",
    "gender": "m",
    "class": "noun",
    "topic": "monetary"
  },
  {
    "german": "gelenk",
    "english": "joint",
    "gender": "n",
    "class": "verb",
    "topic": "anatomy"
  },
  {
    "german": "gemüse",
    "english": "vegetables",
    "gender": "n",
    "class": "noun",
    "topic": "food"
  },
  {
    "german": "gepäck",
    "english": "luggage",
    "gender": "n",
    "class": "noun",
    "topic": "container"
  },
  {
    "german": "geschieden",
    "english": "divorced",
    "gender": "",
    "class": "adj",
    "topic": "family"
  },
  {
    "german": "geschirr",
    "english": "dishes / tableware",
    "gender": "n",
    "class": "noun",
    "topic": "furniture"
  },
  {
    "german": "geschirrspüler",
    "english": "dish washer",
    "gender": "m",
    "class": "noun",
    "topic": "furniture"
  },
  {
    "german": "gesicht",
    "english": "face",
    "gender": "n",
    "class": "verb",
    "topic": "anatomy"
  },
  {
    "german": "gespräch",
    "english": "dialogue",
    "gender": "n",
    "class": "noun",
    "topic": ""
  },
  {
    "german": "gewinnen",
    "english": "to win",
    "gender": "",
    "class": "verb",
    "topic": ""
  },
  {
    "german": "gitarre",
    "english": "guitar",
    "gender": "f",
    "class": "noun",
    "topic": "furniture"
  },
  {
    "german": "glas",
    "english": "glass",
    "gender": "n",
    "class": "noun",
    "topic": "furniture"
  },
  {
    "german": "glauben",
    "english": "to believe",
    "gender": "",
    "class": "verb",
    "topic": ""
  },
  {
    "german": "gleich",
    "english": "like / equal",
    "gender": "",
    "class": "adj",
    "topic": ""
  },
  {
    "german": "glücklich",
    "english": "happy",
    "gender": "",
    "class": "adj",
    "topic": ""
  },
  {
    "german": "graben",
    "english": "to dig",
    "gender": "",
    "class": "verb",
    "topic": ""
  },
  {
    "german": "gramm",
    "english": "gram",
    "gender": "n",
    "class": "noun",
    "topic": "monetary"
  },
  {
    "german": "grau",
    "english": "gray",
    "gender": "",
    "class": "adj",
    "topic": "color"
  },
  {
    "german": "groß",
    "english": "big",
    "gender": "",
    "class": "adj",
    "topic": ""
  },
  {
    "german": "großmutter",
    "english": "grandmother",
    "gender": "f",
    "class": "noun",
    "topic": "family"
  },
  {
    "german": "großvater",
    "english": "grandfather",
    "gender": "m",
    "class": "noun",
    "topic": "family"
  },
  {
    "german": "grün",
    "english": "green",
    "gender": "",
    "class": "adj",
    "topic": "color"
  },
  {
    "german": "gucken",
    "english": "to look",
    "gender": "",
    "class": "verb",
    "topic": ""
  },
  {
    "german": "gut",
    "english": "good",
    "gender": "",
    "class": "adj",
    "topic": ""
  },
  {
    "german": "haar",
    "english": "hair",
    "gender": "n",
    "class": "verb",
    "topic": "anatomy"
  },
  {
    "german": "haben",
    "english": "to have",
    "gender": "",
    "class": "verb",
    "topic": ""
  },
  {
    "german": "hackfleisch",
    "english": "minced meat",
    "gender": "n",
    "class": "noun",
    "topic": "food"
  },
  {
    "german": "hahn",
    "english": "cock",
    "gender": "m",
    "class": "noun",
    "topic": "animal"
  },
  {
    "german": "hahn",
    "english": "tap",
    "gender": "m",
    "class": "noun",
    "topic": "house"
  },
  {
    "german": "hähnchen",
    "english": "chicken",
    "gender": "n",
    "class": "noun",
    "topic": "animal"
  },
  {
    "german": "hals",
    "english": "neck",
    "gender": "m",
    "class": "verb",
    "topic": "anatomy"
  },
  {
    "german": "halten",
    "english": "to hold",
    "gender": "",
    "class": "verb",
    "topic": ""
  },
  {
    "german": "hand",
    "english": "hand",
    "gender": "f",
    "class": "verb",
    "topic": "anatomy"
  },
  {
    "german": "handy",
    "english": "mobile phone",
    "gender": "n",
    "class": "noun",
    "topic": "furniture"
  },
  {
    "german": "hässlich",
    "english": "ugly",
    "gender": "",
    "class": "adj",
    "topic": ""
  },
  {
    "german": "hauptstadt",
    "english": "capital city",
    "gender": "f",
    "class": "noun",
    "topic": ""
  },
  {
    "german": "haus",
    "english": "house",
    "gender": "n",
    "class": "noun",
    "topic": "house"
  },
  {
    "german": "haut",
    "english": "skin",
    "gender": "f",
    "class": "verb",
    "topic": "anatomy"
  },
  {
    "german": "heft",
    "english": "notebook",
    "gender": "n",
    "class": "noun",
    "topic": "office"
  },
  {
    "german": "heißen",
    "english": "to be called",
    "gender": "",
    "class": "verb",
    "topic": ""
  },
  {
    "german": "hell",
    "english": "light (color)",
    "gender": "",
    "class": "adj",
    "topic": "color"
  },
  {
    "german": "hellrot",
    "english": "light red",
    "gender": "",
    "class": "adj",
    "topic": "color"
  },
  {
    "german": "herbst",
    "english": "autumn",
    "gender": "m",
    "class": "noun",
    "topic": "nature"
  },
  {
    "german": "herd",
    "english": "oven",
    "gender": "m",
    "class": "noun",
    "topic": "furniture"
  },
  {
    "german": "herz",
    "english": "heart",
    "gender": "n",
    "class": "verb",
    "topic": "anatomy"
  },
  {
    "german": "hier",
    "english": "here",
    "gender": "",
    "class": "adv",
    "topic": ""
  },
  {
    "german": "hilfen",
    "english": "to help",
    "gender": "",
    "class": "verb",
    "topic": ""
  },
  {
    "german": "hinzufügen",
    "english": "to add",
    "gender": "",
    "class": "verb",
    "topic": ""
  },
  {
    "german": "hoch",
    "english": "tall / high",
    "gender": "",
    "class": "adj",
    "topic": ""
  },
  {
    "german": "hoffen",
    "english": "to hope",
    "gender": "",
    "class": "verb",
    "topic": ""
  },
  {
    "german": "hören",
    "english": "to hear",
    "gender": "",
    "class": "verb",
    "topic": ""
  },
  {
    "german": "hotel",
    "english": "hotel",
    "gender": "n",
    "class": "noun",
    "topic": ""
  },
  {
    "german": "huhn",
    "english": "chicken",
    "gender": "n",
    "class": "noun",
    "topic": "animal"
  },
  {
    "german": "hühnchen",
    "english": "(young) chicken",
    "gender": "n",
    "class": "noun",
    "topic": "animal"
  },
  {
    "german": "hund",
    "english": "dog",
    "gender": "m",
    "class": "noun",
    "topic": "animal"
  },
  {
    "german": "hunger",
    "english": "hunger",
    "gender": "m",
    "class": "noun",
    "topic": "anatomy"
  },
  {
    "german": "idee",
    "english": "idea",
    "gender": "f",
    "class": "noun",
    "topic": ""
  },
  {
    "german": "improvisieren",
    "english": "to improvise",
    "gender": "",
    "class": "verb",
    "topic": ""
  },
  {
    "german": "in Ordnung bringen",
    "english": "to fix",
    "gender": "",
    "class": "verb",
    "topic": ""
  },
  {
    "german": "ingenieur",
    "english": "engineer",
    "gender": "m",
    "class": "noun",
    "topic": "profession"
  },
  {
    "german": "inhaber",
    "english": "owener",
    "gender": "m",
    "class": "noun",
    "topic": "profession"
  },
  {
    "german": "jagen",
    "english": "to hunt",
    "gender": "",
    "class": "verb",
    "topic": ""
  },
  {
    "german": "jahr",
    "english": "year",
    "gender": "n",
    "class": "noun",
    "topic": ""
  },
  {
    "german": "käfer",
    "english": "beetle",
    "gender": "m",
    "class": "noun",
    "topic": "animal"
  },
  {
    "german": "kajüte",
    "english": "cabin",
    "gender": "f",
    "class": "noun",
    "topic": "transportation"
  },
  {
    "german": "kamel",
    "english": "camel",
    "gender": "n",
    "class": "noun",
    "topic": "animal"
  },
  {
    "german": "kamera",
    "english": "camera",
    "gender": "f",
    "class": "noun",
    "topic": "furniture"
  },
  {
    "german": "kanin",
    "english": "rabbit",
    "gender": "n",
    "class": "noun",
    "topic": "animal"
  },
  {
    "german": "kaninchen",
    "english": "rabbit",
    "gender": "n",
    "class": "noun",
    "topic": "animal"
  },
  {
    "german": "kartoffel",
    "english": "potato",
    "gender": "f",
    "class": "noun",
    "topic": "food"
  },
  {
    "german": "katze",
    "english": "cat",
    "gender": "f",
    "class": "noun",
    "topic": "animal"
  },
  {
    "german": "kaufen",
    "english": "to buy",
    "gender": "",
    "class": "verb",
    "topic": ""
  },
  {
    "german": "kehle",
    "english": "throat",
    "gender": "f",
    "class": "verb",
    "topic": "anatomy"
  },
  {
    "german": "keiler",
    "english": "boar",
    "gender": "m",
    "class": "noun",
    "topic": "animal"
  },
  {
    "german": "kellner",
    "english": "waiter",
    "gender": "m",
    "class": "noun",
    "topic": "profession"
  },
  {
    "german": "kellnerin",
    "english": "waiter",
    "gender": "f",
    "class": "noun",
    "topic": "profession"
  },
  {
    "german": "kilo",
    "english": "kilo",
    "gender": "n",
    "class": "noun",
    "topic": "monetary"
  },
  {
    "german": "kind",
    "english": "child",
    "gender": "n",
    "class": "noun",
    "topic": "family"
  },
  {
    "german": "kinderzimmer",
    "english": "child's bedroom",
    "gender": "n",
    "class": "noun",
    "topic": "house"
  },
  {
    "german": "kiste",
    "english": "box",
    "gender": "f",
    "class": "noun",
    "topic": "container"
  },
  {
    "german": "kiwi",
    "english": "kiwi",
    "gender": "f",
    "class": "noun",
    "topic": "food"
  },
  {
    "german": "klein",
    "english": "small",
    "gender": "",
    "class": "adj",
    "topic": ""
  },
  {
    "german": "kleingeld",
    "english": "change (money)",
    "gender": "n",
    "class": "noun",
    "topic": "monetary"
  },
  {
    "german": "klettern",
    "english": "to climb",
    "gender": "",
    "class": "verb",
    "topic": ""
  },
  {
    "german": "knie",
    "english": "knee",
    "gender": "n",
    "class": "verb",
    "topic": "anatomy"
  },
  {
    "german": "knöchel",
    "english": "ankle",
    "gender": "m",
    "class": "verb",
    "topic": "anatomy"
  },
  {
    "german": "knochen",
    "english": "bone",
    "gender": "m",
    "class": "verb",
    "topic": "anatomy"
  },
  {
    "german": "koch",
    "english": "cook",
    "gender": "m",
    "class": "noun",
    "topic": "profession"
  },
  {
    "german": "kochen",
    "english": "to cook",
    "gender": "",
    "class": "verb",
    "topic": ""
  },
  {
    "german": "kocher",
    "english": "cooker / burner",
    "gender": "m",
    "class": "noun",
    "topic": "furniture"
  },
  {
    "german": "köchin",
    "english": "cook",
    "gender": "f",
    "class": "noun",
    "topic": "profession"
  },
  {
    "german": "kommen",
    "english": "to come",
    "gender": "",
    "class": "verb",
    "topic": ""
  },
  {
    "german": "kontext",
    "english": "context",
    "gender": "m",
    "class": "noun",
    "topic": ""
  },
  {
    "german": "kopf",
    "english": "head",
    "gender": "m",
    "class": "verb",
    "topic": "anatomy"
  },
  {
    "german": "kosten",
    "english": "to cost",
    "gender": "",
    "class": "verb",
    "topic": "monetary"
  },
  {
    "german": "kraft",
    "english": "strength / power",
    "gender": "f",
    "class": "noun",
    "topic": ""
  },
  {
    "german": "krankenschwester",
    "english": "nurse",
    "gender": "f",
    "class": "noun",
    "topic": "profession"
  },
  {
    "german": "krankenwagen",
    "english": "ambulance",
    "gender": "m",
    "class": "noun",
    "topic": "transportation"
  },
  {
    "german": "krokodil",
    "english": "crocodile",
    "gender": "n",
    "class": "noun",
    "topic": "animal"
  },
  {
    "german": "küche",
    "english": "kitchen",
    "gender": "f",
    "class": "noun",
    "topic": "house"
  },
  {
    "german": "kuchen",
    "english": "cake",
    "gender": "m",
    "class": "noun",
    "topic": "food"
  },
  {
    "german": "kuh",
    "english": "cow",
    "gender": "f",
    "class": "noun",
    "topic": "animal"
  },
  {
    "german": "kühlschrank",
    "english": "fridge",
    "gender": "m",
    "class": "noun",
    "topic": "furniture"
  },
  {
    "german": "kuli",
    "english": "pen",
    "gender": "m",
    "class": "noun",
    "topic": "office"
  },
  {
    "german": "kunde",
    "english": "client",
    "gender": "m",
    "class": "noun",
    "topic": "profession"
  },
  {
    "german": "kundin",
    "english": "client",
    "gender": "f",
    "class": "noun",
    "topic": "profession"
  },
  {
    "german": "kuss",
    "english": "kiss",
    "gender": "m",
    "class": "noun",
    "topic": "anatomy"
  },
  {
    "german": "lächeln",
    "english": "to smile",
    "gender": "",
    "class": "verb",
    "topic": ""
  },
  {
    "german": "lachen",
    "english": "to laugh",
    "gender": "",
    "class": "verb",
    "topic": ""
  },
  {
    "german": "laden",
    "english": "shop",
    "gender": "m",
    "class": "noun",
    "topic": "monetary"
  },
  {
    "german": "lampe",
    "english": "lamp",
    "gender": "f",
    "class": "noun",
    "topic": "furniture"
  },
  {
    "german": "laptop",
    "english": "laptop",
    "gender": "m",
    "class": "noun",
    "topic": "furniture"
  },
  {
    "german": "lassen",
    "english": "to leave (as)",
    "gender": "",
    "class": "verb",
    "topic": ""
  },
  {
    "german": "lauch",
    "english": "leek",
    "gender": "m",
    "class": "noun",
    "topic": "food"
  },
  {
    "german": "laufen",
    "english": "to run",
    "gender": "",
    "class": "verb",
    "topic": ""
  },
  {
    "german": "leben",
    "english": "to live",
    "gender": "",
    "class": "verb",
    "topic": ""
  },
  {
    "german": "lebensstil",
    "english": "lifestyle",
    "gender": "m",
    "class": "noun",
    "topic": ""
  },
  {
    "german": "leber",
    "english": "liver",
    "gender": "f",
    "class": "verb",
    "topic": "anatomy"
  },
  {
    "german": "leberfleck",
    "english": "mole",
    "gender": "m",
    "class": "noun",
    "topic": "anatomy"
  },
  {
    "german": "lehren",
    "english": "to teach",
    "gender": "",
    "class": "verb",
    "topic": ""
  },
  {
    "german": "lehrer",
    "english": "teacher",
    "gender": "m",
    "class": "noun",
    "topic": "profession"
  },
  {
    "german": "lektion",
    "english": "lesson",
    "gender": "f",
    "class": "noun",
    "topic": ""
  },
  {
    "german": "lernen",
    "english": "to learn",
    "gender": "",
    "class": "verb",
    "topic": ""
  },
  {
    "german": "lesen",
    "english": "to read",
    "gender": "",
    "class": "verb",
    "topic": ""
  },
  {
    "german": "leute",
    "english": "people",
    "gender": "p",
    "class": "noun",
    "topic": "family"
  },
  {
    "german": "licht",
    "english": "light",
    "gender": "n",
    "class": "noun",
    "topic": "nature"
  },
  {
    "german": "lieben",
    "english": "to love",
    "gender": "",
    "class": "verb",
    "topic": ""
  },
  {
    "german": "lineal",
    "english": "ruler",
    "gender": "n",
    "class": "noun",
    "topic": "office"
  },
  {
    "german": "lüge",
    "english": "lie",
    "gender": "f",
    "class": "noun",
    "topic": ""
  },
  {
    "german": "lügen",
    "english": "to lie",
    "gender": "",
    "class": "verb",
    "topic": ""
  },
  {
    "german": "lunge",
    "english": "lung",
    "gender": "f",
    "class": "verb",
    "topic": "anatomy"
  },
  {
    "german": "luxus",
    "english": "luxury",
    "gender": "m",
    "class": "noun",
    "topic": ""
  },
  {
    "german": "magen",
    "english": "stomach",
    "gender": "m",
    "class": "verb",
    "topic": "anatomy"
  },
  {
    "german": "malen",
    "english": "to paint (picture, person)",
    "gender": "",
    "class": "verb",
    "topic": ""
  },
  {
    "german": "mann",
    "english": "man",
    "gender": "m",
    "class": "noun",
    "topic": "family"
  },
  {
    "german": "männer",
    "english": "men",
    "gender": "p",
    "class": "noun",
    "topic": "family"
  },
  {
    "german": "markt",
    "english": "market",
    "gender": "m",
    "class": "noun",
    "topic": "monetary"
  },
  {
    "german": "mathematik",
    "english": "mathematics",
    "gender": "f",
    "class": "noun",
    "topic": "office"
  },
  {
    "german": "matratze",
    "english": "mattress",
    "gender": "f",
    "class": "noun",
    "topic": "house"
  },
  {
    "german": "maus",
    "english": "mouse",
    "gender": "f",
    "class": "noun",
    "topic": "animal"
  },
  {
    "german": "mehl",
    "english": "honey",
    "gender": "n",
    "class": "noun",
    "topic": "food"
  },
  {
    "german": "meinen",
    "english": "to mean (= refer to)",
    "gender": "",
    "class": "verb",
    "topic": ""
  },
  {
    "german": "mensch",
    "english": "person",
    "gender": "m",
    "class": "noun",
    "topic": "family"
  },
  {
    "german": "mikrofon",
    "english": "microphone",
    "gender": "n",
    "class": "noun",
    "topic": "furniture"
  },
  {
    "german": "milch",
    "english": "milk",
    "gender": "f",
    "class": "noun",
    "topic": "food"
  },
  {
    "german": "minaralwasser",
    "english": "mineral water",
    "gender": "n",
    "class": "noun",
    "topic": "food"
  },
  {
    "german": "möbel",
    "english": "furniture",
    "gender": "n",
    "class": "noun",
    "topic": "furniture"
  },
  {
    "german": "monat",
    "english": "month",
    "gender": "m",
    "class": "noun",
    "topic": "time"
  },
  {
    "german": "morgen",
    "english": "morning",
    "gender": "m",
    "class": "noun",
    "topic": "time"
  },
  {
    "german": "motorrad",
    "english": "motorbike",
    "gender": "n",
    "class": "noun",
    "topic": "transportation"
  },
  {
    "german": "mund",
    "english": "mouth",
    "gender": "m",
    "class": "verb",
    "topic": "anatomy"
  },
  {
    "german": "münze",
    "english": "coin",
    "gender": "f",
    "class": "noun",
    "topic": "monetary"
  },
  {
    "german": "musik",
    "english": "music",
    "gender": "f",
    "class": "noun",
    "topic": "entertainment"
  },
  {
    "german": "musiker",
    "english": "musician",
    "gender": "m",
    "class": "noun",
    "topic": "profession"
  },
  {
    "german": "muskel",
    "english": "muscle",
    "gender": "m",
    "class": "verb",
    "topic": "anatomy"
  },
  {
    "german": "mutter",
    "english": "mother",
    "gender": "f",
    "class": "noun",
    "topic": "family"
  },
  {
    "german": "mütter",
    "english": "mothers",
    "gender": "p",
    "class": "noun",
    "topic": "family"
  },
  {
    "german": "nacht",
    "english": "night",
    "gender": "f",
    "class": "noun",
    "topic": "time"
  },
  {
    "german": "nagel",
    "english": "nail",
    "gender": "m",
    "class": "verb",
    "topic": "anatomy"
  },
  {
    "german": "nase",
    "english": "nose",
    "gender": "f",
    "class": "verb",
    "topic": "anatomy"
  },
  {
    "german": "nass",
    "english": "wet",
    "gender": "",
    "class": "adj",
    "topic": ""
  },
  {
    "german": "nass machen",
    "english": "to wet",
    "gender": "",
    "class": "verb",
    "topic": ""
  },
  {
    "german": "neffe",
    "english": "nephew",
    "gender": "m",
    "class": "noun",
    "topic": "family"
  },
  {
    "german": "nerv",
    "english": "nerve",
    "gender": "m",
    "class": "verb",
    "topic": "anatomy"
  },
  {
    "german": "nicht",
    "english": "not",
    "gender": "",
    "class": "adv",
    "topic": ""
  },
  {
    "german": "nichte",
    "english": "niece",
    "gender": "f",
    "class": "noun",
    "topic": "family"
  },
  {
    "german": "noch",
    "english": "still",
    "gender": "",
    "class": "adv",
    "topic": ""
  },
  {
    "german": "nummer",
    "english": "number",
    "gender": "f",
    "class": "noun",
    "topic": "office"
  },
  {
    "german": "öffnen",
    "english": "to open",
    "gender": "",
    "class": "verb",
    "topic": ""
  },
  {
    "german": "ohr",
    "english": "ear",
    "gender": "n",
    "class": "verb",
    "topic": "anatomy"
  },
  {
    "german": "oma",
    "english": "grandmother",
    "gender": "f",
    "class": "noun",
    "topic": "family"
  },
  {
    "german": "onkel",
    "english": "uncle",
    "gender": "m",
    "class": "noun",
    "topic": "family"
  },
  {
    "german": "opa",
    "english": "grandfather",
    "gender": "m",
    "class": "noun",
    "topic": "family"
  },
  {
    "german": "orange",
    "english": "orange",
    "gender": "f",
    "class": "noun",
    "topic": "food"
  },
  {
    "german": "packung",
    "english": "packet",
    "gender": "f",
    "class": "noun",
    "topic": "container"
  },
  {
    "german": "parfum",
    "english": "perfume",
    "gender": "n",
    "class": "noun",
    "topic": "accessories"
  },
  {
    "german": "partner",
    "english": "partner",
    "gender": "m",
    "class": "noun",
    "topic": "family"
  },
  {
    "german": "partnerin",
    "english": "partner",
    "gender": "f",
    "class": "noun",
    "topic": "family"
  },
  {
    "german": "pause",
    "english": "pause",
    "gender": "f",
    "class": "noun",
    "topic": "office"
  },
  {
    "german": "pfanne",
    "english": "pan",
    "gender": "f",
    "class": "noun",
    "topic": "furniture"
  },
  {
    "german": "pfannkuchen",
    "english": "pancake",
    "gender": "m",
    "class": "noun",
    "topic": "food"
  },
  {
    "german": "pferd",
    "english": "horse",
    "gender": "n",
    "class": "noun",
    "topic": "animal"
  },
  {
    "german": "pflanzen",
    "english": "to plant",
    "gender": "",
    "class": "verb",
    "topic": ""
  },
  {
    "german": "pfund",
    "english": "pound",
    "gender": "n",
    "class": "noun",
    "topic": "monetary"
  },
  {
    "german": "photo",
    "english": "photo",
    "gender": "n",
    "class": "noun",
    "topic": "furniture"
  },
  {
    "german": "pizza",
    "english": "pizza",
    "gender": "f",
    "class": "noun",
    "topic": "food"
  },
  {
    "german": "platz",
    "english": "place / space",
    "gender": "m",
    "class": "noun",
    "topic": ""
  },
  {
    "german": "plz",
    "english": "post code",
    "gender": "f",
    "class": "noun",
    "topic": ""
  },
  {
    "german": "polizeiauto",
    "english": "police car",
    "gender": "n",
    "class": "noun",
    "topic": "transportation"
  },
  {
    "german": "polizist",
    "english": "policeman",
    "gender": "m",
    "class": "noun",
    "topic": "profession"
  },
  {
    "german": "polizisten",
    "english": "policemen",
    "gender": "p",
    "class": "noun",
    "topic": "profession"
  },
  {
    "german": "polizistin",
    "english": "policewoman",
    "gender": "f",
    "class": "noun",
    "topic": "profession"
  },
  {
    "german": "preis",
    "english": "price",
    "gender": "m",
    "class": "noun",
    "topic": "monetary"
  },
  {
    "german": "probieren",
    "english": "to try",
    "gender": "",
    "class": "verb",
    "topic": ""
  },
  {
    "german": "radio",
    "english": "radio",
    "gender": "n",
    "class": "noun",
    "topic": "furniture"
  },
  {
    "german": "rätsel",
    "english": "riddle",
    "gender": "n",
    "class": "noun",
    "topic": ""
  },
  {
    "german": "rauch",
    "english": "smoke",
    "gender": "m",
    "class": "noun",
    "topic": "element"
  },
  {
    "german": "regal",
    "english": "shelf",
    "gender": "n",
    "class": "noun",
    "topic": "furniture"
  },
  {
    "german": "reh",
    "english": "deer",
    "gender": "n",
    "class": "noun",
    "topic": "animal"
  },
  {
    "german": "reinigung",
    "english": "cleaning",
    "gender": "f",
    "class": "noun",
    "topic": "house"
  },
  {
    "german": "reis",
    "english": "rice",
    "gender": "m",
    "class": "noun",
    "topic": "food"
  },
  {
    "german": "reisen",
    "english": "to travel",
    "gender": "",
    "class": "verb",
    "topic": "transportation"
  },
  {
    "german": "reporter",
    "english": "reporter",
    "gender": "m",
    "class": "noun",
    "topic": "profession"
  },
  {
    "german": "reporterin",
    "english": "reporter",
    "gender": "f",
    "class": "noun",
    "topic": "profession"
  },
  {
    "german": "rest",
    "english": "rest",
    "gender": "m",
    "class": "noun",
    "topic": ""
  },
  {
    "german": "rezept",
    "english": "recipe",
    "gender": "n",
    "class": "noun",
    "topic": "food"
  },
  {
    "german": "rolle",
    "english": "role",
    "gender": "f",
    "class": "noun",
    "topic": "entertainment"
  },
  {
    "german": "rollenspiel",
    "english": "role play",
    "gender": "n",
    "class": "noun",
    "topic": "entertainment"
  },
  {
    "german": "rot",
    "english": "red",
    "gender": "",
    "class": "adj",
    "topic": "color"
  },
  {
    "german": "rücken",
    "english": "back",
    "gender": "m",
    "class": "verb",
    "topic": "anatomy"
  },
  {
    "german": "ruhen",
    "english": "to rest",
    "gender": "",
    "class": "verb",
    "topic": ""
  },
  {
    "german": "saft",
    "english": "juice",
    "gender": "m",
    "class": "noun",
    "topic": "food"
  },
  {
    "german": "säfte",
    "english": "juice",
    "gender": "p",
    "class": "noun",
    "topic": "food"
  },
  {
    "german": "sagen",
    "english": "to say",
    "gender": "",
    "class": "verb",
    "topic": ""
  },
  {
    "german": "sahne",
    "english": "cream",
    "gender": "f",
    "class": "noun",
    "topic": "food"
  },
  {
    "german": "salz",
    "english": "salt",
    "gender": "n",
    "class": "noun",
    "topic": "food"
  },
  {
    "german": "sänger",
    "english": "singer",
    "gender": "m",
    "class": "noun",
    "topic": "profession"
  },
  {
    "german": "sängerin",
    "english": "singer",
    "gender": "f",
    "class": "noun",
    "topic": "profession"
  },
  {
    "german": "sänitäter",
    "english": "first-aid attendant",
    "gender": "m",
    "class": "noun",
    "topic": "profession"
  },
  {
    "german": "sauber",
    "english": "clean",
    "gender": "",
    "class": "adj",
    "topic": ""
  },
  {
    "german": "schenkel",
    "english": "thigh",
    "gender": "m",
    "class": "verb",
    "topic": "anatomy"
  },
  {
    "german": "schere",
    "english": "scissors",
    "gender": "f",
    "class": "noun",
    "topic": "office"
  },
  {
    "german": "schicken",
    "english": "to send",
    "gender": "",
    "class": "verb",
    "topic": ""
  },
  {
    "german": "schienbein",
    "english": "shin",
    "gender": "n",
    "class": "verb",
    "topic": "anatomy"
  },
  {
    "german": "schlafen",
    "english": "to sleep",
    "gender": "",
    "class": "verb",
    "topic": "anatomy"
  },
  {
    "german": "schlafzimmer",
    "english": "bedroom",
    "gender": "n",
    "class": "noun",
    "topic": "house"
  },
  {
    "german": "schlange",
    "english": "snake",
    "gender": "f",
    "class": "noun",
    "topic": "animal"
  },
  {
    "german": "schlecht",
    "english": "bad",
    "gender": "",
    "class": "adj",
    "topic": ""
  },
  {
    "german": "schließen",
    "english": "to close",
    "gender": "",
    "class": "verb",
    "topic": ""
  },
  {
    "german": "schlucken",
    "english": "to swallow",
    "gender": "",
    "class": "verb",
    "topic": ""
  },
  {
    "german": "schlüssel",
    "english": "key",
    "gender": "m",
    "class": "noun",
    "topic": "house"
  },
  {
    "german": "schmal",
    "english": "narrow",
    "gender": "",
    "class": "adj",
    "topic": ""
  },
  {
    "german": "schmetterling",
    "english": "butterfly",
    "gender": "m",
    "class": "noun",
    "topic": "animal"
  },
  {
    "german": "schmutz",
    "english": "dirt",
    "gender": "m",
    "class": "noun",
    "topic": ""
  },
  {
    "german": "schneiden",
    "english": "to cut",
    "gender": "",
    "class": "verb",
    "topic": ""
  },
  {
    "german": "schön",
    "english": "beautiful",
    "gender": "",
    "class": "adj",
    "topic": ""
  },
  {
    "german": "schrank",
    "english": "cupboard",
    "gender": "m",
    "class": "noun",
    "topic": "furniture"
  },
  {
    "german": "schreiben",
    "english": "to write",
    "gender": "",
    "class": "verb",
    "topic": "office"
  },
  {
    "german": "schreibtisch",
    "english": "desk",
    "gender": "m",
    "class": "noun",
    "topic": "furniture"
  },
  {
    "german": "schule",
    "english": "school",
    "gender": "f",
    "class": "noun",
    "topic": ""
  },
  {
    "german": "schulter",
    "english": "shoulder",
    "gender": "f",
    "class": "verb",
    "topic": "anatomy"
  },
  {
    "german": "schwach",
    "english": "weak",
    "gender": "",
    "class": "adj",
    "topic": ""
  },
  {
    "german": "schwager",
    "english": "brother-in-law",
    "gender": "m",
    "class": "noun",
    "topic": "family"
  },
  {
    "german": "schwägerin",
    "english": "sister-in-law",
    "gender": "f",
    "class": "noun",
    "topic": "family"
  },
  {
    "german": "schwanz",
    "english": "tail",
    "gender": "m",
    "class": "noun",
    "topic": "animal"
  },
  {
    "german": "schwarz",
    "english": "black",
    "gender": "",
    "class": "adj",
    "topic": "color"
  },
  {
    "german": "schwein",
    "english": "pig",
    "gender": "n",
    "class": "noun",
    "topic": "animal"
  },
  {
    "german": "schweinefleisch",
    "english": "pork",
    "gender": "n",
    "class": "noun",
    "topic": "animal"
  },
  {
    "german": "schwer",
    "english": "difficult",
    "gender": "",
    "class": "adj",
    "topic": ""
  },
  {
    "german": "schwester",
    "english": "sister",
    "gender": "f",
    "class": "noun",
    "topic": "family"
  },
  {
    "german": "schwiegermutter",
    "english": "mother-in-law",
    "gender": "f",
    "class": "noun",
    "topic": "family"
  },
  {
    "german": "schwiegersohn",
    "english": "son-in-law",
    "gender": "m",
    "class": "noun",
    "topic": "family"
  },
  {
    "german": "schwiegertochter",
    "english": "daughter-in-law",
    "gender": "f",
    "class": "noun",
    "topic": "family"
  },
  {
    "german": "schwiegervater",
    "english": "father-in-law",
    "gender": "m",
    "class": "noun",
    "topic": "family"
  },
  {
    "german": "schwimmen",
    "english": "to swim",
    "gender": "",
    "class": "verb",
    "topic": ""
  },
  {
    "german": "schwören",
    "english": "to swear",
    "gender": "",
    "class": "verb",
    "topic": ""
  },
  {
    "german": "segelboot",
    "english": "sailing boat",
    "gender": "n",
    "class": "noun",
    "topic": "transportation"
  },
  {
    "german": "segnen",
    "english": "to bless",
    "gender": "",
    "class": "verb",
    "topic": ""
  },
  {
    "german": "sehen",
    "english": "to see",
    "gender": "",
    "class": "verb",
    "topic": ""
  },
  {
    "german": "sein",
    "english": "to be",
    "gender": "",
    "class": "verb",
    "topic": ""
  },
  {
    "german": "seite",
    "english": "page",
    "gender": "f",
    "class": "noun",
    "topic": ""
  },
  {
    "german": "sessel",
    "english": "armchair",
    "gender": "m",
    "class": "noun",
    "topic": "furniture"
  },
  {
    "german": "sich erinnern",
    "english": "to remember",
    "gender": "",
    "class": "verb",
    "topic": ""
  },
  {
    "german": "sich verhalten",
    "english": "to behave",
    "gender": "",
    "class": "verb",
    "topic": ""
  },
  {
    "german": "sich verstellen",
    "english": "to pretend",
    "gender": "",
    "class": "verb",
    "topic": ""
  },
  {
    "german": "singen",
    "english": "to sing",
    "gender": "",
    "class": "verb",
    "topic": ""
  },
  {
    "german": "sklave",
    "english": "slave",
    "gender": "m",
    "class": "noun",
    "topic": "profession"
  },
  {
    "german": "sofa",
    "english": "sofa",
    "gender": "n",
    "class": "noun",
    "topic": "furniture"
  },
  {
    "german": "sofort",
    "english": "immediately",
    "gender": "",
    "class": "adv",
    "topic": ""
  },
  {
    "german": "sohn",
    "english": "son",
    "gender": "m",
    "class": "noun",
    "topic": "family"
  },
  {
    "german": "söhne",
    "english": "sons",
    "gender": "p",
    "class": "noun",
    "topic": "family"
  },
  {
    "german": "sommer",
    "english": "summer",
    "gender": "m",
    "class": "noun",
    "topic": "nature"
  },
  {
    "german": "sonder",
    "english": "without",
    "gender": "",
    "class": "prep",
    "topic": ""
  },
  {
    "german": "sonderangebot",
    "english": "special offer",
    "gender": "n",
    "class": "noun",
    "topic": "monetary"
  },
  {
    "german": "sonne",
    "english": "sun",
    "gender": "f",
    "class": "noun",
    "topic": "nature"
  },
  {
    "german": "sonst",
    "english": "else",
    "gender": "",
    "class": "adv",
    "topic": ""
  },
  {
    "german": "speck",
    "english": "fat",
    "gender": "m",
    "class": "noun",
    "topic": "food"
  },
  {
    "german": "spielen",
    "english": "to play",
    "gender": "",
    "class": "verb",
    "topic": "sport"
  },
  {
    "german": "spielen",
    "english": "to act (roleplay)",
    "gender": "",
    "class": "verb",
    "topic": ""
  },
  {
    "german": "spieler",
    "english": "player",
    "gender": "m",
    "class": "noun",
    "topic": "sport"
  },
  {
    "german": "spielerin",
    "english": "player",
    "gender": "f",
    "class": "noun",
    "topic": "profession"
  },
  {
    "german": "spinat",
    "english": "spinach",
    "gender": "m",
    "class": "noun",
    "topic": "food"
  },
  {
    "german": "spinne",
    "english": "spider",
    "gender": "f",
    "class": "noun",
    "topic": "animal"
  },
  {
    "german": "sport",
    "english": "sport",
    "gender": "m",
    "class": "noun",
    "topic": "sport"
  },
  {
    "german": "sprache",
    "english": "language",
    "gender": "f",
    "class": "noun",
    "topic": ""
  },
  {
    "german": "sprechen",
    "english": "to speak",
    "gender": "",
    "class": "verb",
    "topic": ""
  },
  {
    "german": "staat",
    "english": "state",
    "gender": "m",
    "class": "noun",
    "topic": ""
  },
  {
    "german": "stadt",
    "english": "city",
    "gender": "f",
    "class": "noun",
    "topic": ""
  },
  {
    "german": "steigen",
    "english": "to rise",
    "gender": "",
    "class": "verb",
    "topic": ""
  },
  {
    "german": "sterben",
    "english": "to die",
    "gender": "",
    "class": "verb",
    "topic": ""
  },
  {
    "german": "stern",
    "english": "star",
    "gender": "m",
    "class": "noun",
    "topic": "nature"
  },
  {
    "german": "stiefmutter",
    "english": "stepmother",
    "gender": "f",
    "class": "noun",
    "topic": "family"
  },
  {
    "german": "stiefsohn",
    "english": "stepson",
    "gender": "m",
    "class": "noun",
    "topic": "family"
  },
  {
    "german": "stieftochter",
    "english": "stepdaughter",
    "gender": "f",
    "class": "noun",
    "topic": "family"
  },
  {
    "german": "stiefvater",
    "english": "stepfather",
    "gender": "m",
    "class": "noun",
    "topic": "family"
  },
  {
    "german": "stift",
    "english": "pen",
    "gender": "m",
    "class": "noun",
    "topic": "office"
  },
  {
    "german": "stil",
    "english": "style",
    "gender": "m",
    "class": "noun",
    "topic": ""
  },
  {
    "german": "stören",
    "english": "to disturb",
    "gender": "",
    "class": "verb",
    "topic": ""
  },
  {
    "german": "straße",
    "english": "street",
    "gender": "f",
    "class": "noun",
    "topic": ""
  },
  {
    "german": "streichen",
    "english": "to paint (wall, doog)",
    "gender": "",
    "class": "verb",
    "topic": ""
  },
  {
    "german": "student",
    "english": "student",
    "gender": "m",
    "class": "noun",
    "topic": "profession"
  },
  {
    "german": "studentin",
    "english": "student",
    "gender": "f",
    "class": "noun",
    "topic": "profession"
  },
  {
    "german": "studieren",
    "english": "to study",
    "gender": "",
    "class": "verb",
    "topic": ""
  },
  {
    "german": "stuhl",
    "english": "chair",
    "gender": "m",
    "class": "noun",
    "topic": "furniture"
  },
  {
    "german": "stühle",
    "english": "chairs",
    "gender": "p",
    "class": "noun",
    "topic": "furniture"
  },
  {
    "german": "suchen",
    "english": "to look for",
    "gender": "",
    "class": "verb",
    "topic": ""
  },
  {
    "german": "supermarkt",
    "english": "supermarket",
    "gender": "m",
    "class": "noun",
    "topic": "monetary"
  },
  {
    "german": "tabelle",
    "english": "table (sheet)",
    "gender": "f",
    "class": "noun",
    "topic": "office"
  },
  {
    "german": "tablet",
    "english": "tablet",
    "gender": "n",
    "class": "noun",
    "topic": "furniture"
  },
  {
    "german": "tag",
    "english": "day",
    "gender": "m",
    "class": "noun",
    "topic": "time"
  },
  {
    "german": "taille",
    "english": "waist",
    "gender": "f",
    "class": "verb",
    "topic": "anatomy"
  },
  {
    "german": "tante",
    "english": "aunt",
    "gender": "f",
    "class": "noun",
    "topic": "family"
  },
  {
    "german": "tasche",
    "english": "bag",
    "gender": "f",
    "class": "noun",
    "topic": "container"
  },
  {
    "german": "tauschen",
    "english": "to exchange / to swap",
    "gender": "",
    "class": "verb",
    "topic": ""
  },
  {
    "german": "taxi",
    "english": "taxi",
    "gender": "n",
    "class": "noun",
    "topic": "transportation"
  },
  {
    "german": "tee",
    "english": "tee",
    "gender": "m",
    "class": "noun",
    "topic": "food"
  },
  {
    "german": "telefon",
    "english": "phone",
    "gender": "n",
    "class": "noun",
    "topic": "furniture"
  },
  {
    "german": "teppich",
    "english": "carpet",
    "gender": "m",
    "class": "noun",
    "topic": "furniture"
  },
  {
    "german": "teuer",
    "english": "expensive",
    "gender": "",
    "class": "adj",
    "topic": ""
  },
  {
    "german": "tier",
    "english": "animal",
    "gender": "n",
    "class": "noun",
    "topic": "animal"
  },
  {
    "german": "tierarzt",
    "english": "veterinatian",
    "gender": "m",
    "class": "noun",
    "topic": "profession"
  },
  {
    "german": "tisch",
    "english": "table",
    "gender": "m",
    "class": "noun",
    "topic": "furniture"
  },
  {
    "german": "tochter",
    "english": "daughter",
    "gender": "f",
    "class": "noun",
    "topic": "family"
  },
  {
    "german": "toilette",
    "english": "toilet",
    "gender": "f",
    "class": "noun",
    "topic": "house"
  },
  {
    "german": "tomate",
    "english": "tomato",
    "gender": "f",
    "class": "noun",
    "topic": "food"
  },
  {
    "german": "töten",
    "english": "to kill",
    "gender": "",
    "class": "verb",
    "topic": ""
  },
  {
    "german": "tourist",
    "english": "tourist",
    "gender": "m",
    "class": "noun",
    "topic": "profession"
  },
  {
    "german": "tragen",
    "english": "to carry",
    "gender": "",
    "class": "verb",
    "topic": ""
  },
  {
    "german": "traum",
    "english": "dream",
    "gender": "m",
    "class": "noun",
    "topic": ""
  },
  {
    "german": "träumen",
    "english": "to dream",
    "gender": "",
    "class": "verb",
    "topic": ""
  },
  {
    "german": "trinken",
    "english": "to drink",
    "gender": "",
    "class": "verb",
    "topic": "food"
  },
  {
    "german": "trocknen",
    "english": "to dry",
    "gender": "",
    "class": "verb",
    "topic": ""
  },
  {
    "german": "türkei",
    "english": "turkey",
    "gender": "f",
    "class": "noun",
    "topic": "country"
  },
  {
    "german": "üben",
    "english": "practise",
    "gender": "",
    "class": "verb",
    "topic": ""
  },
  {
    "german": "übersetzen",
    "english": "to translate",
    "gender": "",
    "class": "verb",
    "topic": ""
  },
  {
    "german": "übung",
    "english": "exercise",
    "gender": "f",
    "class": "noun",
    "topic": ""
  },
  {
    "german": "uhr",
    "english": "clock",
    "gender": "f",
    "class": "noun",
    "topic": "furniture"
  },
  {
    "german": "ukraine",
    "english": "ukraine",
    "gender": "f",
    "class": "noun",
    "topic": "country"
  },
  {
    "german": "unbedingt",
    "english": "unconditional",
    "gender": "",
    "class": "adj",
    "topic": ""
  },
  {
    "german": "unterbrechen",
    "english": "to interrupt",
    "gender": "",
    "class": "verb",
    "topic": ""
  },
  {
    "german": "unterhaltung",
    "english": "entertainment",
    "gender": "f",
    "class": "noun",
    "topic": "entertainment"
  },
  {
    "german": "untersuchen",
    "english": "to investigate",
    "gender": "",
    "class": "verb",
    "topic": ""
  },
  {
    "german": "vater",
    "english": "father",
    "gender": "m",
    "class": "noun",
    "topic": "family"
  },
  {
    "german": "verbessern",
    "english": "to improve",
    "gender": "",
    "class": "verb",
    "topic": ""
  },
  {
    "german": "verfluchen",
    "english": "to put a curse on",
    "gender": "",
    "class": "verb",
    "topic": ""
  },
  {
    "german": "vergessen",
    "english": "to forget",
    "gender": "",
    "class": "verb",
    "topic": ""
  },
  {
    "german": "verheiratet",
    "english": "married",
    "gender": "",
    "class": "adj",
    "topic": "family"
  },
  {
    "german": "verkaufen",
    "english": "to sell",
    "gender": "",
    "class": "verb",
    "topic": ""
  },
  {
    "german": "verkäufer",
    "english": "salesman",
    "gender": "m",
    "class": "noun",
    "topic": "profession"
  },
  {
    "german": "verkäuferin",
    "english": "saleswoman",
    "gender": "f",
    "class": "noun",
    "topic": "profession"
  },
  {
    "german": "verlassen",
    "english": "to leave (from)",
    "gender": "",
    "class": "verb",
    "topic": ""
  },
  {
    "german": "verlieben",
    "english": "to fall in love",
    "gender": "",
    "class": "verb",
    "topic": ""
  },
  {
    "german": "verlieren",
    "english": "to lose",
    "gender": "",
    "class": "verb",
    "topic": ""
  },
  {
    "german": "versprechen",
    "english": "to promise",
    "gender": "",
    "class": "verb",
    "topic": ""
  },
  {
    "german": "verstanden",
    "english": "to understand",
    "gender": "",
    "class": "verb",
    "topic": ""
  },
  {
    "german": "versuchen",
    "english": "to try",
    "gender": "",
    "class": "verb",
    "topic": ""
  },
  {
    "german": "vogel",
    "english": "bird",
    "gender": "m",
    "class": "noun",
    "topic": "animal"
  },
  {
    "german": "wagen",
    "english": "car",
    "gender": "m",
    "class": "noun",
    "topic": "transportation"
  },
  {
    "german": "wanze",
    "english": "bug",
    "gender": "f",
    "class": "noun",
    "topic": "animal"
  },
  {
    "german": "warten",
    "english": "to wait",
    "gender": "",
    "class": "verb",
    "topic": ""
  },
  {
    "german": "waschbecken",
    "english": "sink",
    "gender": "n",
    "class": "noun",
    "topic": "furniture"
  },
  {
    "german": "waschen",
    "english": "wash",
    "gender": "",
    "class": "verb",
    "topic": ""
  },
  {
    "german": "waschmaschine",
    "english": "washing machine",
    "gender": "f",
    "class": "noun",
    "topic": "furniture"
  },
  {
    "german": "wasser",
    "english": "water",
    "gender": "n",
    "class": "noun",
    "topic": "food"
  },
  {
    "german": "wein",
    "english": "wine",
    "gender": "m",
    "class": "noun",
    "topic": "food"
  },
  {
    "german": "weinen",
    "english": "to cry",
    "gender": "",
    "class": "verb",
    "topic": ""
  },
  {
    "german": "weiß",
    "english": "white",
    "gender": "",
    "class": "adj",
    "topic": "color"
  },
  {
    "german": "weiter",
    "english": "further",
    "gender": "",
    "class": "adj",
    "topic": ""
  },
  {
    "german": "werbung",
    "english": "advertising",
    "gender": "f",
    "class": "noun",
    "topic": "monetary"
  },
  {
    "german": "wichtig",
    "english": "important",
    "gender": "",
    "class": "adj",
    "topic": ""
  },
  {
    "german": "wiederholen",
    "english": "to repeat",
    "gender": "",
    "class": "verb",
    "topic": ""
  },
  {
    "german": "winter",
    "english": "winter",
    "gender": "m",
    "class": "noun",
    "topic": "nature"
  },
  {
    "german": "wohnen",
    "english": "to live at",
    "gender": "",
    "class": "verb",
    "topic": "house"
  },
  {
    "german": "wohnung",
    "english": "apartment",
    "gender": "f",
    "class": "noun",
    "topic": "house"
  },
  {
    "german": "wolf",
    "english": "wolf",
    "gender": "m",
    "class": "noun",
    "topic": "animal"
  },
  {
    "german": "wollen",
    "english": "to want",
    "gender": "",
    "class": "verb",
    "topic": ""
  },
  {
    "german": "wort",
    "english": "word",
    "gender": "n",
    "class": "noun",
    "topic": "office"
  },
  {
    "german": "wörter",
    "english": "words",
    "gender": "p",
    "class": "noun",
    "topic": "office"
  },
  {
    "german": "wunderschön",
    "english": "wonderful",
    "gender": "",
    "class": "adj",
    "topic": ""
  },
  {
    "german": "wünschen",
    "english": "to wish",
    "gender": "",
    "class": "verb",
    "topic": ""
  },
  {
    "german": "wurm",
    "english": "worm",
    "gender": "m",
    "class": "noun",
    "topic": "animal"
  },
  {
    "german": "wurst",
    "english": "sausage",
    "gender": "f",
    "class": "noun",
    "topic": "food"
  },
  {
    "german": "würstchen",
    "english": "little sausage",
    "gender": "n",
    "class": "noun",
    "topic": "food"
  },
  {
    "german": "zahl",
    "english": "number",
    "gender": "f",
    "class": "noun",
    "topic": "monetary"
  },
  {
    "german": "zahlen",
    "english": "to count",
    "gender": "",
    "class": "verb",
    "topic": "monetary"
  },
  {
    "german": "zahn",
    "english": "tooth",
    "gender": "m",
    "class": "noun",
    "topic": "anatomy"
  },
  {
    "german": "zecke",
    "english": "ticket",
    "gender": "f",
    "class": "noun",
    "topic": "animal"
  },
  {
    "german": "zeh",
    "english": "toe",
    "gender": "m",
    "class": "verb",
    "topic": "anatomy"
  },
  {
    "german": "zeit",
    "english": "time",
    "gender": "f",
    "class": "noun",
    "topic": "nature"
  },
  {
    "german": "ziehen",
    "english": "to draw (move by puling)",
    "gender": "",
    "class": "verb",
    "topic": ""
  },
  {
    "german": "zimmer",
    "english": "room",
    "gender": "n",
    "class": "noun",
    "topic": "house"
  },
  {
    "german": "zoo",
    "english": "zoo",
    "gender": "m",
    "class": "noun",
    "topic": "animal"
  },
  {
    "german": "zucker",
    "english": "sugar",
    "gender": "m",
    "class": "noun",
    "topic": "food"
  },
  {
    "german": "zufrieden",
    "english": "satisfied",
    "gender": "",
    "class": "adj",
    "topic": ""
  },
  {
    "german": "zug",
    "english": "train",
    "gender": "m",
    "class": "noun",
    "topic": "transportation"
  },
  {
    "german": "zuhören",
    "english": "to listen",
    "gender": "",
    "class": "verb",
    "topic": ""
  },
  {
    "german": "zunge",
    "english": "tong",
    "gender": "f",
    "class": "noun",
    "topic": "anatomy"
  },
  {
    "german": "zwiebel",
    "english": "onion",
    "gender": "f",
    "class": "noun",
    "topic": "food"
  }
]
